cloudspec/__init__.py
cloudspec/conf.py
cloudspec/scripts.py
pop_create_idem/conf.py
pop_create_idem/version.py
pop_create_idem/cloudspec/init.py
pop_create_idem/cloudspec/create/auto_state.py
pop_create_idem/cloudspec/create/docs.py
pop_create_idem/cloudspec/create/exec_modules.py
pop_create_idem/cloudspec/create/sls.py
pop_create_idem/cloudspec/create/state_modules.py
pop_create_idem/cloudspec/create/templates.py
pop_create_idem/cloudspec/create/tests.py
pop_create_idem/cloudspec/create/tool.py
pop_create_idem/cloudspec/create/contracts/init.py
pop_create_idem/cloudspec/customize/contracts/init.py
pop_create_idem/cloudspec/parse/example.py
pop_create_idem/cloudspec/parse/function.py
pop_create_idem/cloudspec/parse/param.py
pop_create_idem/cloudspec/parse/plugin.py
pop_create_idem/cloudspec/template/auto_state.py
pop_create_idem/cloudspec/template/exec.py
pop_create_idem/cloudspec/template/plugin.py
pop_create_idem/cloudspec/template/state.py
pop_create_idem/cloudspec/template/test.py
pop_create_idem/cloudspec/template/tool.py
pop_create_idem/pop_create/idem_cloud/init.py
pop_create_idem/pop_create/idem_cloud/hooks/post_gen_project.py
pop_create_idem/pop_create/idem_cloud/hooks/pre_gen_project.py
pop_create_idem/pop_create/idem_cloud/{{cookiecutter.root_dir}}/README.rst
pop_create_idem/pop_create/idem_cloud/{{cookiecutter.root_dir}}/build.conf
pop_create_idem/pop_create/idem_cloud/{{cookiecutter.root_dir}}/example/absent/init.sls
pop_create_idem/pop_create/idem_cloud/{{cookiecutter.root_dir}}/example/present/init.sls
pop_create_idem/pop_create/idem_cloud/{{cookiecutter.root_dir}}/requirements/base.txt
pop_create_idem/pop_create/idem_cloud/{{cookiecutter.root_dir}}/requirements/tests.in
pop_create_idem/pop_create/idem_cloud/{{cookiecutter.root_dir}}/tests/integration/conftest.py
pop_create_idem/pop_create/idem_cloud/{{cookiecutter.root_dir}}/tests/unit/conftest.py
pop_create_idem-4.5.1.dist-info/LICENSE
pop_create_idem-4.5.1.dist-info/METADATA
pop_create_idem-4.5.1.dist-info/WHEEL
pop_create_idem-4.5.1.dist-info/entry_points.txt
pop_create_idem-4.5.1.dist-info/top_level.txt
pop_create_idem-4.5.1.dist-info/RECORD
