Metadata-Version: 2.1
Name: pop-create-idem
Version: 4.5.1
Home-page: https://docs.idemproject.io/pop-create-idem/en/latest/index.html
Author: VMware, Inc.
Author-email: idemproject@vmware.com
License: Apache Software License 2.0
Project-URL: Code, https://gitlab.com/vmware/idem/pop-create-idem
Project-URL: Issue tracker, https://gitlab.com/vmware/idem/pop-create-idem/-/issues
Classifier: Environment :: Console
Classifier: Intended Audience :: Developers
Classifier: Intended Audience :: Information Technology
Classifier: Intended Audience :: System Administrators
Classifier: Operating System :: OS Independent
Classifier: Programming Language :: Python
Classifier: Programming Language :: Python :: 3.8
Classifier: Programming Language :: Python :: 3.9
Classifier: Programming Language :: Python :: 3.10
Classifier: Programming Language :: Python :: 3.11
Classifier: Development Status :: 5 - Production/Stable
Classifier: License :: OSI Approved :: Apache Software License
Requires-Python: >=3.8
License-File: LICENSE
Requires-Dist: bs4
Requires-Dist: idem
Requires-Dist: inflect
Requires-Dist: openapi3 ==1.7.0
Requires-Dist: pop
Requires-Dist: pop-config >=12.0.1
Requires-Dist: pop-create >=8.1.0
Requires-Dist: textwrap3
Requires-Dist: tqdm
